simplecalc3/__init__.py
simplecalc3/simplecalc3.py
simplecalc3-0.0.2.dist-info/LICENSE
simplecalc3-0.0.2.dist-info/METADATA
simplecalc3-0.0.2.dist-info/WHEEL
simplecalc3-0.0.2.dist-info/top_level.txt
simplecalc3-0.0.2.dist-info/RECORD
