Metadata-Version: 2.1
Name: simplecalc3
Version: 0.0.2
Summary: Calculator Package
Home-page: https://github.com
Author: Aravind
Author-email: aravind.m@lucence.com
License: UNKNOWN
Project-URL: Bug Tracker, https://github.com
Platform: UNKNOWN
Classifier: Programming Language :: Python :: 3
Classifier: License :: OSI Approved :: MIT License
Classifier: Operating System :: OS Independent
Requires-Python: >=3.8
License-File: LICENSE
